{
  "version": 2,
  "extractor": "papercropper",
  "tables": [
    {
      "url": "assets/tables/openreview/openreview-icml-2025-xfwyb81p5o/table-001.webp",
      "caption": "",
      "page": 0,
      "index": 1,
      "width": 794,
      "height": 519,
      "label": "Table"
    },
    {
      "url": "assets/tables/openreview/openreview-icml-2025-xfwyb81p5o/table-002.webp",
      "caption": "",
      "page": 0,
      "index": 2,
      "width": 902,
      "height": 457,
      "label": "Table"
    },
    {
      "url": "assets/tables/openreview/openreview-icml-2025-xfwyb81p5o/table-003.webp",
      "caption": "",
      "page": 0,
      "index": 3,
      "width": 900,
      "height": 458,
      "label": "Table"
    },
    {
      "url": "assets/tables/openreview/openreview-icml-2025-xfwyb81p5o/table-004.webp",
      "caption": "",
      "page": 0,
      "index": 4,
      "width": 901,
      "height": 179,
      "label": "Table"
    },
    {
      "url": "assets/tables/openreview/openreview-icml-2025-xfwyb81p5o/table-005.webp",
      "caption": "",
      "page": 0,
      "index": 5,
      "width": 1430,
      "height": 423,
      "label": "Table"
    },
    {
      "url": "assets/tables/openreview/openreview-icml-2025-xfwyb81p5o/table-006.webp",
      "caption": "",
      "page": 0,
      "index": 6,
      "width": 1752,
      "height": 458,
      "label": "Table"
    },
    {
      "url": "assets/tables/openreview/openreview-icml-2025-xfwyb81p5o/table-007.webp",
      "caption": "",
      "page": 0,
      "index": 7,
      "width": 1739,
      "height": 465,
      "label": "Table"
    },
    {
      "url": "assets/tables/openreview/openreview-icml-2025-xfwyb81p5o/table-008.webp",
      "caption": "",
      "page": 0,
      "index": 8,
      "width": 1730,
      "height": 463,
      "label": "Table"
    },
    {
      "url": "assets/tables/openreview/openreview-icml-2025-xfwyb81p5o/table-009.webp",
      "caption": "",
      "page": 0,
      "index": 9,
      "width": 1744,
      "height": 465,
      "label": "Table"
    },
    {
      "url": "assets/tables/openreview/openreview-icml-2025-xfwyb81p5o/table-010.webp",
      "caption": "",
      "page": 0,
      "index": 10,
      "width": 1769,
      "height": 494,
      "label": "Table"
    },
    {
      "url": "assets/tables/openreview/openreview-icml-2025-xfwyb81p5o/table-011.webp",
      "caption": "",
      "page": 0,
      "index": 11,
      "width": 1243,
      "height": 241,
      "label": "Table"
    }
  ]
}